NIDAQ-Driver/NIDAQClient.py
NIDAQ-Driver/__init__.py
NIDAQClient/NIDAQClient.py
NIDAQClient/__init__.py
NIDAQClient-0.4.0.dist-info/METADATA
NIDAQClient-0.4.0.dist-info/WHEEL
NIDAQClient-0.4.0.dist-info/top_level.txt
NIDAQClient-0.4.0.dist-info/RECORD
