Metadata-Version: 2.1
Name: NIDAQClient
Version: 0.4.0
Summary: Library for interfacing with NIDAQ devices
Home-page: https://github.com/spanio/NIDAQ-driver
Author: Brian Benchoff
Author-email: brian.benchoff@span.io
Classifier: Development Status :: 3 - Alpha
Classifier: Intended Audience :: Developers
Classifier: License :: OSI Approved :: MIT License
Classifier: Programming Language :: Python :: 3.6
Classifier: Programming Language :: Python :: 3.7
Classifier: Programming Language :: Python :: 3.8
Classifier: Programming Language :: Python :: 3.9
Classifier: Topic :: Software Development :: Libraries :: Python Modules
Requires-Dist: numpy >=1.21.2
Requires-Dist: nidaqmx >=0.5.7
